chromadb_hfds/__init__.py
chromadb_hfds/__main__.py
chromadb_hfds/chroma_import.py
chromadb_hfds/export.py
chromadb_hfds-0.0.2.dist-info/LICENSE.md
chromadb_hfds-0.0.2.dist-info/METADATA
chromadb_hfds-0.0.2.dist-info/WHEEL
chromadb_hfds-0.0.2.dist-info/entry_points.txt
chromadb_hfds-0.0.2.dist-info/RECORD
