Metadata-Version: 2.1
Name: chromadb-hfds
Version: 0.0.2
Summary: Chroma DB Hugging Face Datasets import/export utility
License: MIT
Author: Trayan Azarov
Author-email: trayan.azarov@amikos.tech
Requires-Python: >=3.9,<4.0
Classifier: License :: OSI Approved :: MIT License
Classifier: Programming Language :: Python :: 3
Classifier: Programming Language :: Python :: 3.9
Classifier: Programming Language :: Python :: 3.10
Classifier: Programming Language :: Python :: 3.11
Classifier: Programming Language :: Python :: 3.12
Requires-Dist: chromadb-client (>=0.4.19.dev0,<0.5.0)
Requires-Dist: datasets (>=2.15.0,<3.0.0)
Requires-Dist: onnxruntime (>=1.16.3,<2.0.0)
Requires-Dist: opentelemetry-api (>=1.2.0)
Requires-Dist: opentelemetry-exporter-otlp-proto-grpc (>=1.2.0)
Requires-Dist: opentelemetry-sdk (>=1.2.0)
Requires-Dist: rich (>=13.7.0,<14.0.0)
Requires-Dist: tokenizers (>=0.15.0,<0.16.0)
Requires-Dist: tqdm (>=4.66.1,<5.0.0)
Requires-Dist: typer[all] (>=0.9.0,<0.10.0)
Project-URL: Bug Tracker, https://github.com/amikos-tech/chromadb-hfds/issues
Project-URL: Homepage, https://github.com/amikos-tech/chromadb-hfds/
Project-URL: Source, https://github.com/amikos-tech/chromadb-hfds/
